odoo/addons/stock_receipt_lot_info/README.rst
odoo/addons/stock_receipt_lot_info/__init__.py
odoo/addons/stock_receipt_lot_info/__manifest__.py
odoo/addons/stock_receipt_lot_info/i18n/es.po
odoo/addons/stock_receipt_lot_info/i18n/it.po
odoo/addons/stock_receipt_lot_info/i18n/stock_account_product_run_fifo_hook.pot
odoo/addons/stock_receipt_lot_info/i18n/stock_receipt_lot_info.pot
odoo/addons/stock_receipt_lot_info/migrations/16.0.1.1.0/pre-migration.py
odoo/addons/stock_receipt_lot_info/model/__init__.py
odoo/addons/stock_receipt_lot_info/model/stock_move_line.py
odoo/addons/stock_receipt_lot_info/readme/CONTRIBUTORS.md
odoo/addons/stock_receipt_lot_info/readme/DESCRIPTION.md
odoo/addons/stock_receipt_lot_info/readme/USAGE.md
odoo/addons/stock_receipt_lot_info/static/description/icon.png
odoo/addons/stock_receipt_lot_info/static/description/index.html
odoo/addons/stock_receipt_lot_info/tests/__init__.py
odoo/addons/stock_receipt_lot_info/tests/test_receipt_lot_info.py
odoo/addons/stock_receipt_lot_info/views/stock_move_line_views.xml
odoo_addon_stock_receipt_lot_info-18.0.1.0.0.2.dist-info/METADATA
odoo_addon_stock_receipt_lot_info-18.0.1.0.0.2.dist-info/WHEEL
odoo_addon_stock_receipt_lot_info-18.0.1.0.0.2.dist-info/top_level.txt
odoo_addon_stock_receipt_lot_info-18.0.1.0.0.2.dist-info/RECORD
