Metadata-Version: 2.1
Name: odoo-addon-stock_receipt_lot_info
Version: 18.0.1.0.0.2
Requires-Python: >=3.10
Requires-Dist: odoo==18.0.*
Summary: Be able to introduce more info on lot/serial number while processing a receipt.
Home-page: https://github.com/OCA/stock-logistics-workflow
License: LGPL-3
Author: ForgeFlow, Odoo Community Association (OCA)
Author-email: support@odoo-community.org
Classifier: Programming Language :: Python
Classifier: Framework :: Odoo
Classifier: Framework :: Odoo :: 18.0
Classifier: License :: OSI Approved :: GNU Lesser General Public License v3 (LGPLv3)
